ananas/__init__.py
ananas/ananas.py
ananas/run.py
ananas/default/__init__.py
ananas/default/announce.py
ananas/default/markov.py
ananas/default/roll.py
ananas/default/tracery.py
ananas-1.1.0.dist-info/LICENSE
ananas-1.1.0.dist-info/METADATA
ananas-1.1.0.dist-info/WHEEL
ananas-1.1.0.dist-info/entry_points.txt
ananas-1.1.0.dist-info/top_level.txt
ananas-1.1.0.dist-info/RECORD
