Metadata-Version: 2.1
Name: ananas
Version: 1.1.0
Summary: Mastodon bot framework built on Mastodon.py
Home-page: https://github.com/chronister/ananas
Author: khr
Author-email: chr@cybre.space
License: MIT
Keywords: mastodon microblogging bot
Platform: UNKNOWN
Classifier: Development Status :: 5 - Production/Stable
Classifier: Environment :: Console
Classifier: Intended Audience :: Developers
Classifier: Topic :: Communications
Classifier: License :: OSI Approved :: MIT License
Classifier: Programming Language :: Python :: 3
Classifier: Programming Language :: Python :: 3.3
Requires-Python: ~=3.3
Requires-Dist: Mastodon.py (>=1.3.0)
Requires-Dist: configobj
Requires-Dist: more-itertools
Requires-Dist: requests
